apiterralab/__init__.py
apiterralab/add_one.py
apiterralab/sub_one.py
apiterralab/test.py
apiterralab-0.0.11.dist-info/LICENSE.txt
apiterralab-0.0.11.dist-info/METADATA
apiterralab-0.0.11.dist-info/WHEEL
apiterralab-0.0.11.dist-info/top_level.txt
apiterralab-0.0.11.dist-info/RECORD
