Metadata-Version: 2.1
Name: apiterralab
Version: 0.0.11
Summary: breve descrição
Home-page: UNKNOWN
Author: TerraLab
Author-email: terralab@gmail.com
License: UNKNOWN
Platform: UNKNOWN
License-File: LICENSE.txt
